sinapsis_orpheus_cpp/__init__.py
sinapsis_orpheus_cpp/helpers/__init__.py
sinapsis_orpheus_cpp/helpers/tags.py
sinapsis_orpheus_cpp/templates/__init__.py
sinapsis_orpheus_cpp/templates/orpheus_tts.py
sinapsis_orpheus_cpp/thirdparty/helpers.py
sinapsis_orpheus_cpp-0.1.3.dist-info/licenses/LICENSE
sinapsis_orpheus_cpp-0.1.3.dist-info/METADATA
sinapsis_orpheus_cpp-0.1.3.dist-info/WHEEL
sinapsis_orpheus_cpp-0.1.3.dist-info/top_level.txt
sinapsis_orpheus_cpp-0.1.3.dist-info/RECORD
