Metadata-Version: 2.4
Name: sinapsis-orpheus-cpp
Version: 0.1.3
Summary: Text to speech using Orpheus TTS model
Author-email: SinapsisAI <dev@sinapsis.tech>
Project-URL: Homepage, https://sinapsis.tech
Project-URL: Documentation, https://docs.sinapsis.tech/docs
Project-URL: Tutorials, https://docs.sinapsis.tech/tutorials
Project-URL: Repository, https://github.com/Sinapsis-AI/sinapsis-speech.git
Requires-Python: >=3.10
License-File: LICENSE
Requires-Dist: llama-cpp-python>=0.3.4
Requires-Dist: orpheus-cpp>=0.0.3
Provides-Extra: data-tools
Requires-Dist: sinapsis-data-readers[all]>=0.1.2; extra == "data-tools"
Requires-Dist: sinapsis-data-writers[soundfile]>=0.1.2; extra == "data-tools"
Provides-Extra: all
Requires-Dist: sinapsis-orpheus-cpp[data-tools]; extra == "all"
Dynamic: license-file
